omzutils/__init__.py
omzutils/config.py
omzutils/db_manager.py
omzutils/exceptions.py
omzutils/fc_service.py
omzutils/logging_utils.py
omzutils/performance.py
omzutils/storage.py
tongfujigsaw-0.1.2.dist-info/licenses/LICENSE
wecomutils/__init__.py
wecomutils/wecom/__init__.py
wecomutils/wecom/license.py
wecomutils/wecom/token_cache.py
wecomutils/wecom/wx_api.py
wecomutils/wecom/wx_api_internal.py
wecomutils/wecom/wx_api_providerapp.py
wecomutils/wecom/wx_api_providerdev.py
wecomutils/wecom/wx_crypto.py
wecomutils/wecom/the3party/WXBizMsgCrypt3.py
wecomutils/wecom/the3party/__init__.py
wecomutils/wecom/the3party/ierror.py
tongfujigsaw-0.1.2.dist-info/METADATA
tongfujigsaw-0.1.2.dist-info/WHEEL
tongfujigsaw-0.1.2.dist-info/top_level.txt
tongfujigsaw-0.1.2.dist-info/RECORD
