Metadata-Version: 2.4
Name: tongfujigsaw
Version: 0.1.2
Summary: Comprehensive utility collection for WeChat Work/WeCom integration and general utilities (wecomutils & omzutils)
Author-email: oldManZhang <old_man_zhang@163.com>
Maintainer-email: oldManZhang <old_man_zhang@163.com>
License: MIT
Project-URL: Homepage, https://gitee.com/oldmanzhang/py_wecom_utils
Project-URL: Repository, https://gitee.com/oldmanzhang/py_wecom_utils
Project-URL: Bug Reports, https://gitee.com/oldmanzhang/py_wecom_utils/issues
Project-URL: Documentation, https://gitee.com/oldmanzhang/py_wecom_utils/blob/main/README.md
Project-URL: Source Code, https://gitee.com/oldmanzhang/py_wecom_utils
Keywords: wechat,wecom,utilities,tools,integration,enterprise,tongfu
Classifier: Development Status :: 4 - Beta
Classifier: Intended Audience :: Developers
Classifier: Topic :: Software Development :: Libraries :: Python Modules
Classifier: Topic :: Communications :: Chat
Classifier: Topic :: Office/Business
Classifier: Programming Language :: Python :: 3
Classifier: Programming Language :: Python :: 3.10
Classifier: Programming Language :: Python :: 3.11
Classifier: Programming Language :: Python :: 3.12
Classifier: License :: OSI Approved :: MIT License
Classifier: Operating System :: OS Independent
Requires-Python: >=3.10
License-File: LICENSE
Dynamic: license-file
